gugong/__init__.py
gugong/gugong.py
gugong/data/gugong.json
gugong/models/__init__.py
gugong/models/db.py
gugong/proto/__init__.py
gugong/proto/gugong_pb2.py
gugong-0.5.5.dist-info/LICENSE
gugong-0.5.5.dist-info/METADATA
gugong-0.5.5.dist-info/WHEEL
gugong-0.5.5.dist-info/top_level.txt
gugong-0.5.5.dist-info/RECORD
