Metadata-Version: 2.1
Name: gugong
Version: 0.5.5
Summary: Data library for GuGong, a.k.a as The Palace Museum or The Fobidden City
Home-page: https://github.com/robertwenquan/gugong
Author: Robert Wen
Author-email: saphires@163.com
License: UNKNOWN
Platform: UNKNOWN
Classifier: Programming Language :: Python :: 3
Classifier: License :: OSI Approved :: Apache Software License
Classifier: Operating System :: OS Independent
Requires-Python: >=3.6
